cw_enc/__init__.py
cw_enc/cw_coder.py
cw_enc/driver.py
cw_enc/paddle.py
cw_enc/paddle_cache.py
cw_enc/paddle_mksnd.py
cw_enc/paddle_samplecount.py
cw_enc/parameters.py
cw_enc/wave_blocks.py
morse2sound-1.0.3.dist-info/LICENSE
morse2sound-1.0.3.dist-info/METADATA
morse2sound-1.0.3.dist-info/WHEEL
morse2sound-1.0.3.dist-info/entry_points.txt
morse2sound-1.0.3.dist-info/top_level.txt
morse2sound-1.0.3.dist-info/RECORD
