Metadata-Version: 2.1
Name: morse2sound
Version: 1.0.3
Summary: Software to convert text into Morse code sound files.
Author-email: "Dr. Andreas Krüger, DJ3EI" <dj3ei@famsik.de>
Project-URL: Homepage, https://gitlab.com/4ham/morse2sound
Project-URL: Repository, https://gitlab.com/4ham/morse2sound
Project-URL: Issues, https://gitlab.com/4ham/morse2sound/-/issues
Keywords: Morse,Morsecode,ham,amateur radio,cw
Classifier: Programming Language :: Python :: 3
Classifier: License :: OSI Approved :: MIT License
Classifier: Operating System :: OS Independent
Classifier: Development Status :: 4 - Beta
Classifier: Environment :: Console
Classifier: Intended Audience :: End Users/Desktop
Classifier: Intended Audience :: Education
Classifier: Topic :: Communications :: Ham Radio
Classifier: Topic :: Multimedia :: Sound/Audio :: Sound Synthesis
Requires-Python: >=3.10
License-File: LICENSE
